special_relativity_grapher/__init__.py
special_relativity_grapher/simulation.py
special_relativity_grapher/transforms.py
special_relativity_grapher/utils.py
special_relativity_grapher/visualization.py
special_relativity_grapher-0.1.2.dist-info/licenses/LICENSE
special_relativity_grapher-0.1.2.dist-info/METADATA
special_relativity_grapher-0.1.2.dist-info/WHEEL
special_relativity_grapher-0.1.2.dist-info/top_level.txt
special_relativity_grapher-0.1.2.dist-info/RECORD
